{"properties":{"language":"de-CH","portions":2},"ingredientsArr":[{"id":800,"name":"rote Zwiebel","amount":0.50,"unit":"kleine","groupName":null},{"id":859,"name":"Quark Nature","amount":400.0,"unit":"Gramm","groupName":null},{"id":655,"name":"frische Minze","amount":15.0,"unit":"Blätter","groupName":null},{"id":739,"name":"gemahlener Kreuzkümmel","amount":1.50,"unit":"Teelöffel","groupName":null},{"id":740,"name":"gemahlener schwarzer Pfeffer","amount":0.50,"unit":"Teelöffel","groupName":null},{"id":794,"name":"Salz","amount":1.50,"unit":"Teelöffel","groupName":null},{"id":41,"name":"frische Tomate","amount":0.50,"unit":"kleine","groupName":null},{"id":37,"name":"Gurke","amount":0.50,"unit":"kleine","groupName":null},{"id":73,"name":"Rüebli","amount":0.25,"unit":"kleines","groupName":null}],"toolsArr":{"93":{"name":"grosse Schüssel","amount":1.0},"99":{"name":"Messer","amount":1.0},"59":{"name":"Schneidebrett","amount":1.0},"92":{"name":"Schwingbesen","amount":1.0},"64":{"name":"Raffel","amount":1.0},"58":{"name":"Kochlöffel","amount":1.0}},"actionsArr":{"195":{"name":"Schälen","actionKey":"wash&peel","imageUrl":"http://api.digimeals.com/data/images/Action/knife.svg","stepType":1},"72":{"name":"Zerhacken","actionKey":"chop","imageUrl":"http://api.digimeals.com/data/images/Action/ax.svg","stepType":1},"1":{"name":"Hinzufügen","actionKey":"add","imageUrl":"http://api.digimeals.com/data/images/Action/add.svg","stepType":1},"120":{"name":"Verquirlen","actionKey":"whisk","imageUrl":"http://api.digimeals.com/data/images/Action/whisker.svg","stepType":1},"83":{"name":"Raffeln","actionKey":"grate","imageUrl":"http://api.digimeals.com/data/images/Action/grater.svg","stepType":1},"188":{"name":"Zerhacken","actionKey":"peel&chop","imageUrl":"http://api.digimeals.com/data/images/Action/knife.svg","stepType":1},"197":{"name":"Zerhacken","actionKey":"wash&chop","imageUrl":"http://api.digimeals.com/data/images/Action/knife.svg","stepType":1},"173":{"name":"Hinzufügen","actionKey":"add3","imageUrl":"http://api.digimeals.com/data/images/Action/add.svg","stepType":1},"182":{"name":"Rühren","actionKey":"add&stir","imageUrl":"http://api.digimeals.com/data/images/Action/stir.svg","stepType":1}},"textsArr":["Wasche 0.5 kleine Gurke sanft und schäle sie","Zerhacke die Gurke fein","Füge 400 Gramm Quark Nature zur grossen Schüssel hinzu","Verquirle den Quark Nature während 2 Minuten","Füge die gehackten Gurken zur Schüssel hinzu","Wasche 0.25 kleines Rüebli vorsichtig und schäle es","Raffle das Rüebli fein","Füge die geraffelten Rüebli zur Schüssel hinzu","Schäle 0.5 kleine rote Zwiebel und zerhacke sie fein","Füge die gehackten Zwiebeln zur Schüssel hinzu","Wasche 0.5 kleine frische Tomate vorsichtig und zerhacke sie fein","Füge die gehackten Tomaten zur Schüssel hinzu","Wasche 15 Blätter frische Minze vorsichtig und zerhacke sie fein","Füge die gehackten Minzblätter, 1.5 Teelöffel Salz und 0.5 Teelöffel gemahlenen Pfeffer zur Schüssel hinzu","Füge 1.5 Teelöffel gemahlenen Kreuzkümmel zur Schüssel hinzu und rühre ihn sanft bis ihn gut durchmischt ist",""],"actions":[{"index":0,"action":195,"frame":[0,90],"text":0,"timerValue":0,"nextStep":[1],"passiveMaster":null,"firstParallel":null,"lastParallel":null,"sequenceParallel":[],"constraints":[],"smartOutput":{"toolId":null,"tool":null,"action":"Peel","temperature":null,"duration":90,"ingredients":[{"id":37,"amount":0.5}],"cutSize":null}},{"index":1,"action":72,"frame":[90,60],"text":1,"timerValue":0,"nextStep":[2],"passiveMaster":null,"firstParallel":null,"lastParallel":null,"sequenceParallel":[],"constraints":[{"relation":[0]}],"smartOutput":{"toolId":99,"tool":"knife","action":"Chop","temperature":null,"duration":60,"ingredients":[{"id":37,"amount":0.0}],"cutSize":null}},{"index":2,"action":1,"frame":[150,60],"text":2,"timerValue":0,"nextStep":[3],"passiveMaster":null,"firstParallel":null,"lastParallel":null,"sequenceParallel":[],"constraints":[],"smartOutput":{"toolId":93,"tool":"large bowl","action":"Add","temperature":null,"duration":60,"ingredients":[{"id":859,"amount":400.0}],"cutSize":null}},{"index":3,"action":120,"frame":[210,120],"text":3,"timerValue":120,"nextStep":[4],"passiveMaster":null,"firstParallel":null,"lastParallel":null,"sequenceParallel":[],"constraints":[{"relation":[2]}],"smartOutput":{"toolId":92,"tool":"whisker","action":"Whisk","temperature":null,"duration":120,"ingredients":[{"id":859,"amount":0.0}],"cutSize":null}},{"index":4,"action":1,"frame":[330,60],"text":4,"timerValue":0,"nextStep":[5],"passiveMaster":null,"firstParallel":null,"lastParallel":null,"sequenceParallel":[],"constraints":[{"relation":[1,3]}],"smartOutput":{"toolId":93,"tool":"large bowl","action":"Add","temperature":null,"duration":60,"ingredients":[{"id":37,"amount":0.0}],"cutSize":null}},{"index":5,"action":195,"frame":[390,90],"text":5,"timerValue":0,"nextStep":[6],"passiveMaster":null,"firstParallel":null,"lastParallel":null,"sequenceParallel":[],"constraints":[],"smartOutput":{"toolId":null,"tool":null,"action":"Peel","temperature":null,"duration":90,"ingredients":[{"id":73,"amount":0.25}],"cutSize":null}},{"index":6,"action":83,"frame":[480,60],"text":6,"timerValue":0,"nextStep":[7],"passiveMaster":null,"firstParallel":null,"lastParallel":null,"sequenceParallel":[],"constraints":[{"relation":[5]}],"smartOutput":{"toolId":64,"tool":"grater","action":"Grate","temperature":null,"duration":60,"ingredients":[{"id":73,"amount":0.0}],"cutSize":null}},{"index":7,"action":1,"frame":[540,30],"text":7,"timerValue":0,"nextStep":[8],"passiveMaster":null,"firstParallel":null,"lastParallel":null,"sequenceParallel":[],"constraints":[{"relation":[6,4]}],"smartOutput":{"toolId":93,"tool":"large bowl","action":"Add","temperature":null,"duration":30,"ingredients":[{"id":73,"amount":0.0}],"cutSize":null}},{"index":8,"action":188,"frame":[570,120],"text":8,"timerValue":0,"nextStep":[9],"passiveMaster":null,"firstParallel":null,"lastParallel":null,"sequenceParallel":[],"constraints":[],"smartOutput":{"toolId":99,"tool":"knife","action":"Chop","temperature":null,"duration":120,"ingredients":[{"id":800,"amount":0.5}],"cutSize":null}},{"index":9,"action":1,"frame":[690,60],"text":9,"timerValue":0,"nextStep":[10],"passiveMaster":null,"firstParallel":null,"lastParallel":null,"sequenceParallel":[],"constraints":[{"relation":[7,8]}],"smartOutput":{"toolId":93,"tool":"large bowl","action":"Add","temperature":null,"duration":60,"ingredients":[{"id":800,"amount":0.0}],"cutSize":null}},{"index":10,"action":197,"frame":[750,90],"text":10,"timerValue":0,"nextStep":[11],"passiveMaster":null,"firstParallel":null,"lastParallel":null,"sequenceParallel":[],"constraints":[],"smartOutput":{"toolId":99,"tool":"knife","action":"Chop","temperature":null,"duration":90,"ingredients":[{"id":41,"amount":0.5}],"cutSize":null}},{"index":11,"action":1,"frame":[840,60],"text":11,"timerValue":0,"nextStep":[12],"passiveMaster":null,"firstParallel":null,"lastParallel":null,"sequenceParallel":[],"constraints":[{"relation":[9,10]}],"smartOutput":{"toolId":93,"tool":"large bowl","action":"Add","temperature":null,"duration":60,"ingredients":[{"id":41,"amount":0.0}],"cutSize":null}},{"index":12,"action":197,"frame":[900,90],"text":12,"timerValue":0,"nextStep":[13],"passiveMaster":null,"firstParallel":null,"lastParallel":null,"sequenceParallel":[],"constraints":[],"smartOutput":{"toolId":99,"tool":"knife","action":"Chop","temperature":null,"duration":90,"ingredients":[{"id":655,"amount":15.0}],"cutSize":null}},{"index":13,"action":173,"frame":[990,90],"text":13,"timerValue":0,"nextStep":[14],"passiveMaster":null,"firstParallel":null,"lastParallel":null,"sequenceParallel":[],"constraints":[{"relation":[11,12]}],"smartOutput":{"toolId":93,"tool":"large bowl","action":"Add","temperature":null,"duration":90,"ingredients":[{"id":655,"amount":0.0},{"id":794,"amount":1.5},{"id":740,"amount":0.5}],"cutSize":null}},{"index":14,"action":182,"frame":[1080,150],"text":14,"timerValue":0,"nextStep":[15],"passiveMaster":null,"firstParallel":null,"lastParallel":null,"sequenceParallel":[],"constraints":[{"relation":[13]}],"smartOutput":{"toolId":93,"tool":"large bowl","action":"Stir","temperature":null,"duration":150,"ingredients":[{"id":739,"amount":1.5}],"cutSize":null}},{"index":15,"action":0,"frame":[1230,0],"text":15,"timerValue":0,"nextStep":[],"passiveMaster":null,"firstParallel":null,"lastParallel":null,"sequenceParallel":[],"constraints":[{"relation":[14]}],"smartOutput":null}],"groupsArr":[{"id":35,"title":"Gemüse Raita","imgUrl":"http://api.digimeals.com/data/images/Recipe/PHO_mixed-vegetable-raita-wm.jpg","defaultPortions":2,"portionType":3,"portionPartAmount":null,"portionPieceName":null,"portionPieceMax":null,"portionPieceMin":null,"portionSideName":null}],"fullTime":1230}